setup.cfg
setup.py
WaitForIt.egg-info/PKG-INFO
WaitForIt.egg-info/SOURCES.txt
WaitForIt.egg-info/dependency_links.txt
WaitForIt.egg-info/entry_points.txt
WaitForIt.egg-info/not-zip-safe
WaitForIt.egg-info/paster_plugins.txt
WaitForIt.egg-info/requires.txt
WaitForIt.egg-info/top_level.txt
docs/index.txt
docs/license.txt
waitforit/__init__.py
waitforit/middleware.py
waitforit/testapp.py
waitforit/wsgiapp.py
