Metadata-Version: 1.0
Name: WaitForIt
Version: 0.2
Summary: Provide an intermediate response when a WSGI application slow to respond
Home-page: http://pythonpaste.org/waitforit/
Author: Ian Bicking
Author-email: ianb@colorstudy.com
License: MIT
Keywords: wsgi threads paste
Platform: UNKNOWN
Classifier: Development Status :: 4 - Beta
Classifier: Environment :: Web Environment
Classifier: Intended Audience :: Developers
Classifier: License :: OSI Approved :: MIT License
Classifier: Topic :: Internet :: WWW/HTTP :: WSGI
Classifier: Topic :: Internet :: WWW/HTTP :: WSGI :: Middleware
